caugetch/__init__.py
caugetch/getch.py
caugetch/pause.py
caugetch-0.0.1.dist-info/LICENSE.txt
caugetch-0.0.1.dist-info/METADATA
caugetch-0.0.1.dist-info/WHEEL
caugetch-0.0.1.dist-info/top_level.txt
caugetch-0.0.1.dist-info/RECORD
